{
  "docVersion": "1.0.0",
  "resource": {
    "name": "Maestro Case",
    "kind": "package",
    "apiVersion": "orchestrator.uipath.com/v1",
    "projectKey": "5ef97789-d930-47d8-b290-253cf932bcef",
    "isOverridable": true,
    "dependencies": [],
    "runtimeDependencies": [],
    "files": [],
    "folders": [
      {
        "fullyQualifiedName": "solution_folder"
      }
    ],
    "spec": {
      "fileName": null,
      "fileReference": null,
      "name": "Maestro Case",
      "description": null
    },
    "locks": [],
    "key": "f8621218-dfe6-47a6-8983-f8834db21c51"
  }
}